[{"bug_type":"PURE_FUNCTION","qualifier":"Side-effect free function ow_memcpy_001.","severity":"ERROR","line":17,"column":1,"procedure":"ow_memcpy_001","procedure_start_line":17,"file":"ow_memcpy.c","bug_trace":[{"level":0,"filename":"ow_memcpy.c","line_number":17,"column_number":1,"description":"Side-effect free function ow_memcpy_001"}],"key":"ow_memcpy.c|ow_memcpy_001|PURE_FUNCTION","hash":"da8bcfe21d792abea55713474f7e6715","bug_type_hum":"Pure Function","censored_reason":""},{"bug_type":"PURE_FUNCTION","qualifier":"Side-effect free function ow_memcpy_002_func_001.","severity":"ERROR","line":32,"column":1,"procedure":"ow_memcpy_002_func_001","procedure_start_line":32,"file":"ow_memcpy.c","bug_trace":[{"level":0,"filename":"ow_memcpy.c","line_number":32,"column_number":1,"description":"Side-effect free function ow_memcpy_002_func_001"}],"key":"ow_memcpy.c|ow_memcpy_002_func_001|PURE_FUNCTION","hash":"b4ef3cec0ae6f206396ab33aa78abf64","bug_type_hum":"Pure Function","censored_reason":""},{"bug_type":"BUFFER_OVERRUN_L4","qualifier":"Offset: [0, +oo] Size: 5 by call to `ow_memcpy_002_func_001`.","severity":"ERROR","line":50,"column":2,"procedure":"ow_memcpy_002","procedure_start_line":47,"file":"ow_memcpy.c","bug_trace":[{"level":0,"filename":"ow_memcpy.c","line_number":47,"column_number":1,"description":"Array declaration"},{"level":0,"filename":"ow_memcpy.c","line_number":50,"column_number":2,"description":"Call"},{"level":0,"filename":"ow_memcpy.c","line_number":32,"column_number":1,"description":"<Length trace>"},{"level":1,"filename":"ow_memcpy.c","line_number":32,"column_number":1,"description":"Parameter `*src`"},{"level":1,"filename":"ow_memcpy.c","line_number":37,"column_number":2,"description":"Assignment"},{"level":1,"filename":"ow_memcpy.c","line_number":41,"column_number":8,"description":"Array access: Offset: [0, +oo] Size: 5 by call to `ow_memcpy_002_func_001` "}],"key":"ow_memcpy.c|ow_memcpy_002|BUFFER_OVERRUN_L4","hash":"605e7853935126574eff6a8bf5b0f242","bug_type_hum":"Buffer Overrun L4","censored_reason":""},{"bug_type":"PURE_FUNCTION","qualifier":"Side-effect free function ow_memcpy_002.","severity":"ERROR","line":47,"column":1,"procedure":"ow_memcpy_002","procedure_start_line":47,"file":"ow_memcpy.c","bug_trace":[{"level":0,"filename":"ow_memcpy.c","line_number":47,"column_number":1,"description":"Side-effect free function ow_memcpy_002"}],"key":"ow_memcpy.c|ow_memcpy_002|PURE_FUNCTION","hash":"0dd28328ad7619b597e63fa2aea83ee8","bug_type_hum":"Pure Function","censored_reason":""},{"bug_type":"PURE_FUNCTION","qualifier":"Side-effect free function ow_memcpy_main.","severity":"ERROR","line":58,"column":1,"procedure":"ow_memcpy_main","procedure_start_line":58,"file":"ow_memcpy.c","bug_trace":[{"level":0,"filename":"ow_memcpy.c","line_number":58,"column_number":1,"description":"Side-effect free function ow_memcpy_main"}],"key":"ow_memcpy.c|ow_memcpy_main|PURE_FUNCTION","hash":"63f976341b209daafeef1c00d526eaa5","bug_type_hum":"Pure Function","censored_reason":""}]
