[{"bug_type":"CONDITION_ALWAYS_TRUE","qualifier":"Boolean condition  `!(a>0)` is always false at line 38, column 9.","severity":"WARNING","line":38,"column":9,"procedure":"free_null_pointer_002","procedure_start_line":35,"file":"free_null_pointer.c","bug_trace":[{"level":0,"filename":"free_null_pointer.c","line_number":38,"column_number":9,"description":"Here"}],"key":"free_null_pointer.c|free_null_pointer_002|CONDITION_ALWAYS_TRUE","hash":"c7331ba38f0c267478619bdd95d0b777","bug_type_hum":"Condition Always True","censored_reason":""},{"bug_type":"CONDITION_ALWAYS_TRUE","qualifier":"Boolean condition  `!1` is always false at line 58, column 9.","severity":"WARNING","line":58,"column":9,"procedure":"free_null_pointer_003","procedure_start_line":54,"file":"free_null_pointer.c","bug_trace":[{"level":0,"filename":"free_null_pointer.c","line_number":58,"column_number":9,"description":"Here"}],"key":"free_null_pointer.c|free_null_pointer_003|CONDITION_ALWAYS_TRUE","hash":"970ef34b283ddbfe1cfd182bf963b76c","bug_type_hum":"Condition Always True","censored_reason":""},{"bug_type":"PURE_FUNCTION","qualifier":"Side-effect free function free_null_pointer_004.","severity":"ERROR","line":76,"column":1,"procedure":"free_null_pointer_004","procedure_start_line":76,"file":"free_null_pointer.c","bug_trace":[{"level":0,"filename":"free_null_pointer.c","line_number":76,"column_number":1,"description":"Side-effect free function free_null_pointer_004"}],"key":"free_null_pointer.c|free_null_pointer_004|PURE_FUNCTION","hash":"fefd0795d2e677dfe845b9a1eb653894","bug_type_hum":"Pure Function","censored_reason":""},{"bug_type":"PURE_FUNCTION","qualifier":"Side-effect free function free_null_pointer_006_func_001.","severity":"ERROR","line":127,"column":1,"procedure":"free_null_pointer_006_func_001","procedure_start_line":127,"file":"free_null_pointer.c","bug_trace":[{"level":0,"filename":"free_null_pointer.c","line_number":127,"column_number":1,"description":"Side-effect free function free_null_pointer_006_func_001"}],"key":"free_null_pointer.c|free_null_pointer_006_func_001|PURE_FUNCTION","hash":"848349109c17eff8a184e2143c0d8712","bug_type_hum":"Pure Function","censored_reason":""},{"bug_type":"PURE_FUNCTION","qualifier":"Side-effect free function free_null_pointer_007_func_001.","severity":"ERROR","line":170,"column":1,"procedure":"free_null_pointer_007_func_001","procedure_start_line":170,"file":"free_null_pointer.c","bug_trace":[{"level":0,"filename":"free_null_pointer.c","line_number":170,"column_number":1,"description":"Side-effect free function free_null_pointer_007_func_001"}],"key":"free_null_pointer.c|free_null_pointer_007_func_001|PURE_FUNCTION","hash":"6f5e1a5a57136802eec6645611e6609f","bug_type_hum":"Pure Function","censored_reason":""},{"bug_type":"PURE_FUNCTION","qualifier":"Side-effect free function free_null_pointer_008_func_001.","severity":"ERROR","line":233,"column":1,"procedure":"free_null_pointer_008_func_001","procedure_start_line":233,"file":"free_null_pointer.c","bug_trace":[{"level":0,"filename":"free_null_pointer.c","line_number":233,"column_number":1,"description":"Side-effect free function free_null_pointer_008_func_001"}],"key":"free_null_pointer.c|free_null_pointer_008_func_001|PURE_FUNCTION","hash":"1a981b60d9c4e7361e0505cba120b08d","bug_type_hum":"Pure Function","censored_reason":""},{"bug_type":"CONDITION_ALWAYS_TRUE","qualifier":"Boolean condition  `!1` is always false at line 265, column 9.","severity":"WARNING","line":265,"column":9,"procedure":"free_null_pointer_009_func_001","procedure_start_line":260,"file":"free_null_pointer.c","bug_trace":[{"level":0,"filename":"free_null_pointer.c","line_number":265,"column_number":9,"description":"Here"}],"key":"free_null_pointer.c|free_null_pointer_009_func_001|CONDITION_ALWAYS_TRUE","hash":"943cb94e6598b783577b4d9168d0ad07","bug_type_hum":"Condition Always True","censored_reason":""},{"bug_type":"CONDITION_ALWAYS_TRUE","qualifier":"Boolean condition  `!1` is always false at line 285, column 8.","severity":"WARNING","line":285,"column":8,"procedure":"free_null_pointer_009","procedure_start_line":277,"file":"free_null_pointer.c","bug_trace":[{"level":0,"filename":"free_null_pointer.c","line_number":285,"column_number":8,"description":"Here"}],"key":"free_null_pointer.c|free_null_pointer_009|CONDITION_ALWAYS_TRUE","hash":"0b10f1c5b2ef495005551d232a11257e","bug_type_hum":"Condition Always True","censored_reason":""},{"bug_type":"CONDITION_ALWAYS_TRUE","qualifier":"Boolean condition  `!1` is always false at line 308, column 9.","severity":"WARNING","line":308,"column":9,"procedure":"free_null_pointer_010_func_001","procedure_start_line":304,"file":"free_null_pointer.c","bug_trace":[{"level":0,"filename":"free_null_pointer.c","line_number":308,"column_number":9,"description":"Here"}],"key":"free_null_pointer.c|free_null_pointer_010_func_001|CONDITION_ALWAYS_TRUE","hash":"a1ddccbfab2f640e80858cb5fdd49d4a","bug_type_hum":"Condition Always True","censored_reason":""},{"bug_type":"CONDITION_ALWAYS_TRUE","qualifier":"Boolean condition  `!1` is always false at line 330, column 8.","severity":"WARNING","line":330,"column":8,"procedure":"free_null_pointer_010_func_003","procedure_start_line":327,"file":"free_null_pointer.c","bug_trace":[{"level":0,"filename":"free_null_pointer.c","line_number":330,"column_number":8,"description":"Here"}],"key":"free_null_pointer.c|free_null_pointer_010_func_003|CONDITION_ALWAYS_TRUE","hash":"55a79ee94bff9692033646fbcc9252d3","bug_type_hum":"Condition Always True","censored_reason":""},{"bug_type":"CONDITION_ALWAYS_TRUE","qualifier":"Boolean condition  `!(flag==1)` is always false at line 367, column 3.","severity":"WARNING","line":367,"column":3,"procedure":"free_null_pointer_011_func_001","procedure_start_line":361,"file":"free_null_pointer.c","bug_trace":[{"level":0,"filename":"free_null_pointer.c","line_number":367,"column_number":3,"description":"Here"}],"key":"free_null_pointer.c|free_null_pointer_011_func_001|CONDITION_ALWAYS_TRUE","hash":"84d6d15d88521a29034429cd9ff6cf37","bug_type_hum":"Condition Always True","censored_reason":""},{"bug_type":"CONDITION_ALWAYS_TRUE","qualifier":"Boolean condition  `!(flag==1)` is always false at line 395, column 3.","severity":"WARNING","line":395,"column":3,"procedure":"free_null_pointer_011_func_002","procedure_start_line":390,"file":"free_null_pointer.c","bug_trace":[{"level":0,"filename":"free_null_pointer.c","line_number":395,"column_number":3,"description":"Here"}],"key":"free_null_pointer.c|free_null_pointer_011_func_002|CONDITION_ALWAYS_TRUE","hash":"81fd62edfabebf5e7dc60cf878e3e87d","bug_type_hum":"Condition Always True","censored_reason":""},{"bug_type":"PURE_FUNCTION","qualifier":"Side-effect free function free_null_pointer_012_func_001.","severity":"ERROR","line":434,"column":1,"procedure":"free_null_pointer_012_func_001","procedure_start_line":434,"file":"free_null_pointer.c","bug_trace":[{"level":0,"filename":"free_null_pointer.c","line_number":434,"column_number":1,"description":"Side-effect free function free_null_pointer_012_func_001"}],"key":"free_null_pointer.c|free_null_pointer_012_func_001|PURE_FUNCTION","hash":"f274e4e2040b767eb8c874d02ba7697f","bug_type_hum":"Pure Function","censored_reason":""},{"bug_type":"CONDITION_ALWAYS_TRUE","qualifier":"Boolean condition  `!(1==1)` is always false at line 448, column 54.","severity":"WARNING","line":448,"column":54,"procedure":"free_null_pointer_012","procedure_start_line":443,"file":"free_null_pointer.c","bug_trace":[{"level":0,"filename":"free_null_pointer.c","line_number":448,"column_number":54,"description":"Here"}],"key":"free_null_pointer.c|free_null_pointer_012|CONDITION_ALWAYS_TRUE","hash":"7b3afd7fe5a390e67c5a61796aa262b4","bug_type_hum":"Condition Always True","censored_reason":""},{"bug_type":"CONDITION_ALWAYS_TRUE","qualifier":"Boolean condition  `!(1==1)` is always false at line 454, column 54.","severity":"WARNING","line":454,"column":54,"procedure":"free_null_pointer_012","procedure_start_line":443,"file":"free_null_pointer.c","bug_trace":[{"level":0,"filename":"free_null_pointer.c","line_number":454,"column_number":54,"description":"Here"}],"key":"free_null_pointer.c|free_null_pointer_012|CONDITION_ALWAYS_TRUE","hash":"7b3afd7fe5a390e67c5a61796aa262b4","bug_type_hum":"Condition Always True","censored_reason":""},{"bug_type":"CONDITION_ALWAYS_TRUE","qualifier":"Boolean condition  `!(1==1)` is always false at line 460, column 54.","severity":"WARNING","line":460,"column":54,"procedure":"free_null_pointer_012","procedure_start_line":443,"file":"free_null_pointer.c","bug_trace":[{"level":0,"filename":"free_null_pointer.c","line_number":460,"column_number":54,"description":"Here"}],"key":"free_null_pointer.c|free_null_pointer_012|CONDITION_ALWAYS_TRUE","hash":"7b3afd7fe5a390e67c5a61796aa262b4","bug_type_hum":"Condition Always True","censored_reason":""},{"bug_type":"CONDITION_ALWAYS_TRUE","qualifier":"Boolean condition  `!(flag==10)` is always false at line 456, column 9.","severity":"WARNING","line":456,"column":9,"procedure":"free_null_pointer_012","procedure_start_line":443,"file":"free_null_pointer.c","bug_trace":[{"level":0,"filename":"free_null_pointer.c","line_number":456,"column_number":9,"description":"Here"}],"key":"free_null_pointer.c|free_null_pointer_012|CONDITION_ALWAYS_TRUE","hash":"5e7e609d123b2a95acc8773c9e8f4ad0","bug_type_hum":"Condition Always True","censored_reason":""},{"bug_type":"CONDITION_ALWAYS_TRUE","qualifier":"Boolean condition  `!(flag==10)` is always false at line 462, column 9.","severity":"WARNING","line":462,"column":9,"procedure":"free_null_pointer_012","procedure_start_line":443,"file":"free_null_pointer.c","bug_trace":[{"level":0,"filename":"free_null_pointer.c","line_number":462,"column_number":9,"description":"Here"}],"key":"free_null_pointer.c|free_null_pointer_012|CONDITION_ALWAYS_TRUE","hash":"5e7e609d123b2a95acc8773c9e8f4ad0","bug_type_hum":"Condition Always True","censored_reason":""},{"bug_type":"PURE_FUNCTION","qualifier":"Side-effect free function free_null_pointer_012.","severity":"ERROR","line":443,"column":1,"procedure":"free_null_pointer_012","procedure_start_line":443,"file":"free_null_pointer.c","bug_trace":[{"level":0,"filename":"free_null_pointer.c","line_number":443,"column_number":1,"description":"Side-effect free function free_null_pointer_012"}],"key":"free_null_pointer.c|free_null_pointer_012|PURE_FUNCTION","hash":"0d335095cc9f9ec72c2c5950a0adc69c","bug_type_hum":"Pure Function","censored_reason":""},{"bug_type":"CONDITION_ALWAYS_FALSE","qualifier":"Boolean condition  `(i<=1)` is always false at line 497, column 17.","severity":"WARNING","line":497,"column":17,"procedure":"free_null_pointer_013","procedure_start_line":474,"file":"free_null_pointer.c","bug_trace":[{"level":0,"filename":"free_null_pointer.c","line_number":497,"column_number":17,"description":"Here"}],"key":"free_null_pointer.c|free_null_pointer_013|CONDITION_ALWAYS_FALSE","hash":"46cecac8d6d1ad804be70eef11eb6165","bug_type_hum":"Condition Always False","censored_reason":""},{"bug_type":"CONDITION_ALWAYS_TRUE","qualifier":"Boolean condition  `!(i<=1)` is always false at line 484, column 14.","severity":"WARNING","line":484,"column":14,"procedure":"free_null_pointer_013","procedure_start_line":474,"file":"free_null_pointer.c","bug_trace":[{"level":0,"filename":"free_null_pointer.c","line_number":484,"column_number":14,"description":"Here"}],"key":"free_null_pointer.c|free_null_pointer_013|CONDITION_ALWAYS_TRUE","hash":"d23a6c64a53d7d865d7bc8303c8c9980","bug_type_hum":"Condition Always True","censored_reason":""},{"bug_type":"CONDITION_ALWAYS_TRUE","qualifier":"Boolean condition  `!(i>=0)` is always false at line 484, column 6.","severity":"WARNING","line":484,"column":6,"procedure":"free_null_pointer_013","procedure_start_line":474,"file":"free_null_pointer.c","bug_trace":[{"level":0,"filename":"free_null_pointer.c","line_number":484,"column_number":6,"description":"Here"}],"key":"free_null_pointer.c|free_null_pointer_013|CONDITION_ALWAYS_TRUE","hash":"f160c38223eada472bc8896dc38cda30","bug_type_hum":"Condition Always True","censored_reason":""},{"bug_type":"CONDITION_ALWAYS_TRUE","qualifier":"Boolean condition  `!(i>=0)` is always false at line 491, column 9.","severity":"WARNING","line":491,"column":9,"procedure":"free_null_pointer_013","procedure_start_line":474,"file":"free_null_pointer.c","bug_trace":[{"level":0,"filename":"free_null_pointer.c","line_number":491,"column_number":9,"description":"Here"}],"key":"free_null_pointer.c|free_null_pointer_013|CONDITION_ALWAYS_TRUE","hash":"f160c38223eada472bc8896dc38cda30","bug_type_hum":"Condition Always True","censored_reason":""},{"bug_type":"CONDITION_ALWAYS_TRUE","qualifier":"Boolean condition  `!(i>=0)` is always false at line 497, column 9.","severity":"WARNING","line":497,"column":9,"procedure":"free_null_pointer_013","procedure_start_line":474,"file":"free_null_pointer.c","bug_trace":[{"level":0,"filename":"free_null_pointer.c","line_number":497,"column_number":9,"description":"Here"}],"key":"free_null_pointer.c|free_null_pointer_013|CONDITION_ALWAYS_TRUE","hash":"f160c38223eada472bc8896dc38cda30","bug_type_hum":"Condition Always True","censored_reason":""},{"bug_type":"MEMORY_LEAK","qualifier":"memory dynamically allocated to `*fp1` by call to `calloc()` at line 486, column 26 is not reachable after line 489, column 6.","severity":"ERROR","line":489,"column":6,"procedure":"free_null_pointer_013","procedure_start_line":474,"file":"free_null_pointer.c","bug_trace":[{"level":0,"filename":"free_null_pointer.c","line_number":474,"column_number":1,"description":"start of procedure free_null_pointer_013()"},{"level":0,"filename":"free_null_pointer.c","line_number":477,"column_number":2,"description":""},{"level":0,"filename":"free_null_pointer.c","line_number":478,"column_number":2,"description":""},{"level":0,"filename":"free_null_pointer.c","line_number":479,"column_number":2,"description":""},{"level":0,"filename":"free_null_pointer.c","line_number":480,"column_number":2,"description":""},{"level":0,"filename":"free_null_pointer.c","line_number":483,"column_number":3,"description":""},{"level":0,"filename":"free_null_pointer.c","line_number":484,"column_number":6,"description":"Taking true branch"},{"level":0,"filename":"free_null_pointer.c","line_number":484,"column_number":14,"description":"Taking true branch"},{"level":0,"filename":"free_null_pointer.c","line_number":486,"column_number":9,"description":""},{"level":0,"filename":"free_null_pointer.c","line_number":488,"column_number":6,"description":""},{"level":0,"filename":"free_null_pointer.c","line_number":489,"column_number":6,"description":""},{"level":0,"filename":"free_null_pointer.c","line_number":490,"column_number":6,"description":""},{"level":0,"filename":"free_null_pointer.c","line_number":491,"column_number":9,"description":"Loop condition is true. Entering loop body"},{"level":0,"filename":"free_null_pointer.c","line_number":491,"column_number":17,"description":"Loop condition is true. Entering loop body"},{"level":0,"filename":"free_null_pointer.c","line_number":483,"column_number":3,"description":""},{"level":0,"filename":"free_null_pointer.c","line_number":484,"column_number":6,"description":"Taking true branch"},{"level":0,"filename":"free_null_pointer.c","line_number":484,"column_number":14,"description":"Taking true branch"},{"level":0,"filename":"free_null_pointer.c","line_number":486,"column_number":9,"description":""},{"level":0,"filename":"free_null_pointer.c","line_number":488,"column_number":6,"description":""},{"level":0,"filename":"free_null_pointer.c","line_number":489,"column_number":6,"description":""}],"key":"free_null_pointer.c|free_null_pointer_013|MEMORY_LEAK","node_key":"390b877f047693d83f9ea3b178306716","hash":"e50ce74667dd11f79389169af2934165","bug_type_hum":"Memory Leak","censored_reason":""},{"bug_type":"BUFFER_OVERRUN_L4","qualifier":"Offset: [0, +oo] (⇐ [0, 4] + [0, +oo]) Size: 5 by call to `free_null_pointer_010`.","severity":"ERROR","line":618,"column":3,"procedure":"free_null_pointer_main","procedure_start_line":569,"file":"free_null_pointer.c","bug_trace":[{"level":0,"filename":"free_null_pointer.c","line_number":618,"column_number":3,"description":"Call"},{"level":1,"filename":"free_null_pointer.c","line_number":342,"column_number":1,"description":"Array declaration"},{"level":1,"filename":"free_null_pointer.c","line_number":347,"column_number":5,"description":"Call"},{"level":0,"filename":"free_null_pointer.c","line_number":319,"column_number":1,"description":"<Offset trace>"},{"level":2,"filename":"free_null_pointer.c","line_number":319,"column_number":1,"description":"Parameter `src->strlen`"},{"level":0,"filename":"free_null_pointer.c","line_number":319,"column_number":1,"description":"<Length trace>"},{"level":2,"filename":"free_null_pointer.c","line_number":319,"column_number":1,"description":"Parameter `*src`"},{"level":2,"filename":"free_null_pointer.c","line_number":324,"column_number":5,"description":"Array access: Offset: [0, +oo] (⇐ [0, 4] + [0, +oo]) Size: 5 by call to `free_null_pointer_010` "}],"key":"free_null_pointer.c|free_null_pointer_main|BUFFER_OVERRUN_L4","hash":"63989ae079c620bae9f322fbf0208546","bug_type_hum":"Buffer Overrun L4","censored_reason":""}]
